Workbook
Name Account: #REF!
Name available: #REF!
Name btable: #REF!
Name Contract_Status: #REF!
Name costmonitor: #REF!
Name Current_Level: #REF!
Name Current_Role: #REF!
Name Current_SOW_End_Date: #REF!
Name Current_SOW_Start_Date: #REF!
Name đà: #REF!
Name đasd: #REF!
Name dfhdf: #REF!
Name dsaff: #REF!
Name dsf: #REF!
Name FAP: #REF!
Name fasd: #REF!
Name fghfdj: #REF!
Name First_Start_Date: #REF!
Name FSU: #REF!
Name gf: #REF!
Name hgj: #REF!
Name hwtable: #REF!
Name kl: #REF!
Name Location: #REF!
Name Months_with_SIA: #REF!
Name Name: #REF!
Name positions: #REF!
Name Rate: #REF!
Name rates: #REF!
Name RolesRates: #REF!
Name RolesRatesFY2012: #REF!
Name totalsow: #REF!
Name Type_of_contract: #REF!

Sheet Timesheet
A1: Month | B1: Date | C1: Work Item Type | D1: Surf Request Id/ Project Id | E1: Project Name | F1: Task (Optional) | G1: Resource | H1: Team | I1: Vendor Name | J1: Actual Time (hour)
A2: 46291 | B2: 46266 | C2: Project Task | D2: PJR.0000366783 | E2: PJR.0000366783 - AMA Wave 4 | F2: Production/ BAU Support | G2: Dao Manh Ha | H2: EAI | I2: FPT | J2: 8
A3: 46291 | B3: 46267 | C3: Project Task | D3: PJR.0000366783 | E3: PJR.0000366783 - AMA Wave 4 | F3: Production/ BAU Support | G3: Dao Manh Ha | H3: EAI | I3: FPT | J3: 8
A4: 46291 | B4: 46268 | C4: Project Task | D4: PJR.0000366783 | E4: PJR.0000366783 - AMA Wave 4 | F4: Production/ BAU Support | G4: Dao Manh Ha | H4: EAI | I4: FPT | J4: 8
A5: 46291 | B5: 46269 | C5: Project Task | D5: PJR.0000366783 | E5: PJR.0000366783 - AMA Wave 4 | F5: Production/ BAU Support | G5: Dao Manh Ha | H5: EAI | I5: FPT | J5: 8
A6: 46291 | B6: 46272 | C6: Project Task | D6: PJR.0000366783 | E6: PJR.0000366783 - AMA Wave 4 | F6: Production/ BAU Support | G6: Dao Manh Ha | H6: EAI | I6: FPT | J6: 8
A7: 46291 | B7: 46273 | C7: Project Task | D7: PJR.0000366783 | E7: PJR.0000366783 - AMA Wave 4 | F7: Production/ BAU Support | G7: Dao Manh Ha | H7: EAI | I7: FPT | J7: 8
A8: 46291 | B8: 46274 | C8: Project Task | D8: PJR.0000366783 | E8: PJR.0000366783 - AMA Wave 4 | F8: Production/ BAU Support | G8: Dao Manh Ha | H8: EAI | I8: FPT | J8: 8
A9: 46291 | B9: 46275 | C9: Project Task | D9: PJR.0000366783 | E9: PJR.0000366783 - AMA Wave 4 | F9: Production/ BAU Support | G9: Dao Manh Ha | H9: EAI | I9: FPT | J9: 8
A10: 46291 | B10: 46276 | C10: Project Task | D10: PJR.0000366783 | E10: PJR.0000366783 - AMA Wave 4 | F10: Production/ BAU Support | G10: Dao Manh Ha | H10: EAI | I10: FPT | J10: 8
A11: 46291 | B11: 46277 | C11: Weekend Support | D11: PJR.0000366783 | E11: PJR.0000366783 - AMA Wave 4 | F11: Production/ BAU Support | G11: Dao Manh Ha | H11: EAI | I11: FPT | J11: 8
A12: 46291 | B12: 46278 | C12: Weekend Support | D12: PJR.0000366783 | E12: PJR.0000366783 - AMA Wave 4 | F12: Production/ BAU Support | G12: Dao Manh Ha | H12: EAI | I12: FPT | J12: 8
A13: 46291 | B13: 46279 | C13: Project Task | D13: PJR.0000366783 | E13: PJR.0000366783 - AMA Wave 4 | F13: Production/ BAU Support | G13: Dao Manh Ha | H13: EAI | I13: FPT | J13: 8
... A26: 46291 | B26: 46295 | C26: Project Task | D26: PJR.0000366783 | E26: PJR.0000366783 - AMA Wave 4 | F26: Production/ BAU Support | G26: Dao Manh Ha | H26: EAI | I26: FPT | J26: 8
A27: Sep-26 | B27: 46266 | C27: Leave | D27: Leave | E27: Leave | F27: Annual Leave | G27: Duong Xuan Tung | H27: EAI | I27: FPT | J27: 8
A28: Sep-26 | B28: 46267 | C28: Leave | D28: Leave | E28: Leave | F28: Annual Leave | G28: Duong Xuan Tung | H28: EAI | I28: FPT | J28: 8
A29: Sep-26 | B29: 46268 | C29: Project Task | D29: EAI | E29: Review and fixing issue for EAI IOM modules | G29: Duong Xuan Tung | H29: EAI | I29: FPT | J29: 8
A30: Sep-26 | B30: 46269 | C30: Project Task | D30: EAI | E30: Review and fixing issue for EAI IOM modules | G30: Duong Xuan Tung | H30: EAI | I30: FPT | J30: 8
A31: Sep-26 | B31: 46272 | C31: Project Task | D31: EAI | E31: Review and fixing issue for EAI IOM modules | G31: Duong Xuan Tung | H31: EAI | I31: FPT | J31: 8
A32: Sep-26 | B32: 46273 | C32: Project Task | D32: EAI | E32: AMA_EAI_Internal_ Cross carriage order got stuck in submitted state_ TC32 | G32: Duong Xuan Tung | H32: EAI | I32: FPT | J32: 8
A33: Sep-26 | B33: 46274 | C33: Project Task | D33: EAI | E33: SR26H7850O - INC1551489 FAPI PRD pendingPaymentCall | G33: Duong Xuan Tung | H33: EAI | I33: FPT | J33: 8
A34: Sep-26 | B34: 46275 | C34: Project Task | D34: EAI | E34: ITX_CBG_Orders_Payment Profile Change from Cash to Credit Card – Pending Posting Failed | G34: Duong Xuan Tung | H34: EAI | I34: FPT | J34: 8
A35: Sep-26 | B35: 46276 | C35: Project Task | D35: EAI | E35: Unit testing Order process of IOM | G35: Duong Xuan Tung | H35: EAI | I35: FPT | J35: 8
A36: Sep-26 | B36: 46279 | C36: Project Task | D36: EAI | E36: IOM/SPL Unit Testing | G36: Duong Xuan Tung | H36: EAI | I36: FPT | J36: 8
A37: Sep-26 | B37: 46280 | C37: Project Task | D37: EAI | E37: Check discount component - Broadband Promotional Discount_44.582%_Perpetual | G37: Duong Xuan Tung | H37: EAI | I37: FPT | J37: 8
A38: Sep-26 | B38: 46281 | C38: Project Task | D38: EAI | E38: IOM/SPL Unit Testing | G38: Duong Xuan Tung | H38: EAI | I38: FPT | J38: 8
A39: Sep-26 | B39: 46282 | C39: Project Task | D39: EAI | E39: IOM/SPL Unit Testing | G39: Duong Xuan Tung | H39: EAI | I39: FPT | J39: 8
A40: Sep-26 | B40: 46283 | C40: Project Task | D40: EAI | E40: SR26H7942Q - Enable discount components in BSCS - TS_UAT_SR26H7942Q_TC1.1 - Order failing in Idal | G40: Duong Xuan Tung | H40: EAI | I40: FPT | J40: 8
... A48: Sep-26 | B48: 46295 | C48: Project Task | D48: EAI | E48: Migration & Coding ESPS/IOM | G48: Duong Xuan Tung | H48: EAI | I48: FPT | J48: 8
A49: Sep-26 | B49: 46266 | C49: Project Task | D49: Compax Production Support | E49: Compax Production Support | F49: Compax Production Support | G49: Mary Anne Fabia | H49: AMS | I49: FPT | J49: 8
A50: Sep-26 | B50: 46267 | C50: Project Task | D50: Compax Production Support | E50: Compax Production Support | F50: Compax Production Support | G50: Mary Anne Fabia | H50: AMS | I50: FPT | J50: 8
A51: Sep-26 | B51: 46268 | C51: Project Task | D51: Compax Production Support | E51: Compax Production Support | F51: Compax Production Support | G51: Mary Anne Fabia | H51: AMS | I51: FPT | J51: 8
A52: Sep-26 | B52: 46269 | C52: Project Task | D52: Compax Production Support | E52: Compax Production Support | F52: Compax Production Support | G52: Mary Anne Fabia | H52: AMS | I52: FPT | J52: 8
A53: Sep-26 | B53: 46272 | C53: Project Task | D53: Compax Production Support | E53: Compax Production Support | F53: Compax Production Support | G53: Mary Anne Fabia | H53: AMS | I53: FPT | J53: 8
A54: Sep-26 | B54: 46273 | C54: Project Task | D54: Compax Production Support | E54: Compax Production Support | F54: Compax Production Support | G54: Mary Anne Fabia | H54: AMS | I54: FPT | J54: 8
A55: Sep-26 | B55: 46274 | C55: Project Task | D55: Compax Production Support | E55: Compax Production Support | F55: Compax Production Support | G55: Mary Anne Fabia | H55: AMS | I55: FPT | J55: 8
A56: Sep-26 | B56: 46275 | C56: Project Task | D56: Compax Production Support | E56: Compax Production Support | F56: Compax Production Support | G56: Mary Anne Fabia | H56: AMS | I56: FPT | J56: 8
A57: Sep-26 | B57: 46276 | C57: Project Task | D57: Compax Production Support | E57: Compax Production Support | F57: Compax Production Support | G57: Mary Anne Fabia | H57: AMS | I57: FPT | J57: 8
A58: Sep-26 | B58: 46278 | C58: Weekend support | D58: Compax Production Support | E58: Iphone 18 pre-order | F58: Compax Production Support | G58: Mary Anne Fabia | H58: AMS | I58: FPT | J58: 8
A59: Sep-26 | B59: 46279 | C59: Project Task | D59: Compax Production Support | E59: Compax Production Support | F59: Compax Production Support | G59: Mary Anne Fabia | H59: AMS | I59: FPT | J59: 8
A60: Sep-26 | B60: 46280 | C60: Project Task | D60: Compax Production Support | E60: Compax Production Support | F60: Compax Production Support | G60: Mary Anne Fabia | H60: AMS | I60: FPT | J60: 8
... A96: Sep-26 | B96: 46267 | C96: Leave | D96: Leave | E96: Leave | F96: Annual Leave | G96: Nguyen Hoang | H96: DevOps | I96: FPT | J96: 8
A97: Sep-26 | B97: 46268 | C97: Project Task | D97: CRM | E97: Daily: Health Check RDS Databases, EKS Cluster & Pods HFD DB script execution | G97: Nguyen Hoang | H97: DevOps | I97: FPT | J97: 8
A98: Sep-26 | B98: 46269 | C98: Project Task | D98: CRM | E98: Daily: Health Check RDS Databases, EKS Cluster & Pods ADUAT/TRN Deployment | G98: Nguyen Hoang | H98: DevOps | I98: FPT | J98: 8
A99: Sep-26 | B99: 46272 | C99: Project Task | D99: CRM | E99: Daily: Health Check RDS Databases, EKS Cluster & Pods Multiple TRN/HFD deployment Dryrun deployment in preparation for Prod | G99: Nguyen Hoang | H99: DevOps | I99: FPT | J99: 8
A100: Sep-26 | B100: 46273 | C100: Project Task | D100: CRM | E100: Daily: Health Check RDS Databases, EKS Cluster & Pods Multiple TRN/HFD deployment Dryrun deployment in preparation for Prod | G100: Nguyen Hoang | H100: DevOps | I100: FPT | J100: 8
A101: Sep-26 | B101: 46274 | C101: Project Task | D101: CRM | E101: Daily: Health Check RDS Databases, EKS Cluster & Pods Multiple TRN/HFD deployment Dryrun deployment in preparation for Prod | G101: Nguyen Hoang | H101: DevOps | I101: FPT | J101: 8
A102: Sep-26 | B102: 46275 | C102: Project Task | D102: CRM | E102: Daily: Health Check RDS Databases, EKS Cluster & Pods Multiple TRN/HFD deployment Dryrun deployment in preparation for Prod | G102: Nguyen Hoang | H102: DevOps | I102: FPT | J102: 8
A103: Sep-26 | B103: 46276 | C103: Project Task | D103: CRM | E103: CHG0053691: AD DevHub - Product Catalogue deployment | G103: Nguyen Hoang | H103: DevOps | I103: FPT | J103: 8
A104: Sep-26 | B104: 46278 | C104: Weekend support | D104: CRM | E104: iPhone 18 Launch Monitoring | G104: Nguyen Hoang | H104: DevOps | I104: FPT | J104: 8
A105: Sep-26 | B105: 46279 | C105: Project Task | D105: CRM | E105: Daily: Health Check RDS Databases, EKS Cluster & Pods HFD Deployment / Staging support | G105: Nguyen Hoang | H105: DevOps | I105: FPT | J105: 8
A106: Sep-26 | B106: 46280 | C106: Project Task | D106: CRM | E106: Daily: Health Check RDS Databases, EKS Cluster & Pods HFD Deployment / Staging support | G106: Nguyen Hoang | H106: DevOps | I106: FPT | J106: 8
A107: Sep-26 | B107: 46281 | C107: Project Task | D107: CRM | E107: Daily: Health Check RDS Databases, EKS Cluster & Pods HFD Deployment / Staging support | G107: Nguyen Hoang | H107: DevOps | I107: FPT | J107: 8
A108: Sep-26 | B108: 46282 | C108: Project Task | D108: CRM | E108: Daily: Health Check RDS Databases, EKS Cluster & Pods FinOps initiative: raised request to delete resources | G108: Nguyen Hoang | H108: DevOps | I108: FPT | J108: 8
A109: Sep-26 | B109: 46283 | C109: Project Task | D109: CRM | E109: Daily: Health Check RDS Databases, EKS Cluster & Pods HFD (Staging) support Prod troubleshoot | G109: Nguyen Hoang | H109: DevOps | I109: FPT | J109: 8
A110: Sep-26 | B110: 46286 | C110: Comp-Off / Off-in-Lieu | D110: Comp-Off | E110: Comp-Off | F110: Comp-off for 13-Sep | G110: Nguyen Hoang | H110: DevOps | I110: FPT | J110: 8
A111: Sep-26 | B111: 46287 | C111: Project Task | D111: CRM | E111: Daily: Health Check RDS Databases, EKS Cluster & Pods Multiple TRN/HFD deployment Dryrun deployment in preparation for Prod | G111: Nguyen Hoang | H111: DevOps | I111: FPT | J111: 8
A112: Sep-26 | B112: 46288 | C112: Project Task | D112: CRM | E112: Daily: Health Check RDS Databases, EKS Cluster & Pods Multiple TRN/HFD deployment Dryrun deployment in preparation for Prod | G112: Nguyen Hoang | H112: DevOps | I112: FPT | J112: 8
A113: Sep-26 | B113: 46289 | C113: Project Task | D113: CRM | E113: Daily: Health Check RDS Databases, EKS Cluster & Pods Multiple TRN/HFD deployment Dryrun deployment in preparation for Prod | G113: Nguyen Hoang | H113: DevOps | I113: FPT | J113: 8
A114: Sep-26 | B114: 46290 | C114: Project Task | D114: CRM | E114: Daily: Health Check RDS Databases, EKS Cluster & Pods Multiple TRN/HFD deployment Dryrun deployment in preparation for Prod | G114: Nguyen Hoang | H114: DevOps | I114: FPT | J114: 8
A115: Sep-26 | B115: 46293 | C115: Project Task | D115: CRM | E115: Daily: Health Check RDS Databases, EKS Cluster & Pods | G115: Nguyen Hoang | H115: DevOps | I115: FPT | J115: 8
A116: Sep-26 | B116: 46294 | C116: Project Task | D116: CRM | E116: Daily: Health Check RDS Databases, EKS Cluster & Pods | G116: Nguyen Hoang | H116: DevOps | I116: FPT | J116: 8
A117: Sep-26 | B117: 46295 | C117: Project Task | D117: CRM | E117: Daily: Health Check RDS Databases, EKS Cluster & Pods Investigate and monitor high DB load | G117: Nguyen Hoang | H117: DevOps | I117: FPT | J117: 8
A118: Sep-26 | B118: 46266 | C118: Leave | D118: Leave | E118: Leave | F118: Annual Leave | G118: Trieu Bao Lam | H118: DevOps | I118: FPT | J118: 8
A119: Sep-26 | B119: 46267 | C119: Leave | D119: Leave | E119: Leave | F119: Annual Leave | G119: Trieu Bao Lam | H119: DevOps | I119: FPT | J119: 8
A120: Sep-26 | B120: 46268 | C120: Project Task | D120: CRM | E120: - Join AMA Migration Testing | G120: Trieu Bao Lam | H120: DevOps | I120: FPT | J120: 8
A121: Sep-26 | B121: 46269 | C121: Project Task | D121: CRM | E121: Refactored Jenkins Pipeline: ArgoCD-based Helm Deployment | G121: Trieu Bao Lam | H121: DevOps | I121: FPT | J121: 8
A122: Sep-26 | B122: 46272 | C122: Project Task | D122: CRM | E122: Refactored Jenkins Pipeline: ArgoCD-based Helm Deployment | G122: Trieu Bao Lam | H122: DevOps | I122: FPT | J122: 8
A123: Sep-26 | B123: 46273 | C123: Project Task | D123: CRM | E123: - Prepare helmchart, persistent volume solution, argocd integration for NTS PROD - NTS UAT deployment and testing support | G123: Trieu Bao Lam | H123: DevOps | I123: FPT | J123: 8
A124: Sep-26 | B124: 46274 | C124: Project Task | D124: CRM | E124: - Prepare helmchart, persistent volume solution, argocd integration for NTS PROD - NTS UAT deployment and testing support | G124: Trieu Bao Lam | H124: DevOps | I124: FPT | J124: 8
A125: Sep-26 | B125: 46275 | C125: Project Task | D125: CRM | E125: - Prepare helmchart, persistent volume solution, argocd integration for NTS PROD - NTS UAT deployment and testing support | G125: Trieu Bao Lam | H125: DevOps | I125: FPT | J125: 8
A126: Sep-26 | B126: 46276 | C126: Project Task | D126: CRM | E126: - Prepare helmchart, persistent volume solution, argocd integration for NTS PROD - NTS UAT deployment and testing support | G126: Trieu Bao Lam | H126: DevOps | I126: FPT | J126: 8
A127: Sep-26 | B127: 46279 | C127: Project Task | D127: CRM | E127: - Prepare helmchart, persistent volume solution, argocd integration for NTS PROD - NTS UAT deployment and testing support | G127: Trieu Bao Lam | H127: DevOps | I127: FPT | J127: 8
A128: Sep-26 | B128: 46280 | C128: Project Task | D128: CRM | E128: - Prepare helmchart, persistent volume solution, argocd integration for NTS PROD - NTS UAT deployment and testing support | G128: Trieu Bao Lam | H128: DevOps | I128: FPT | J128: 8
A129: Sep-26 | B129: 46281 | C129: Project Task | D129: CRM | E129: - Prepare helmchart, persistent volume solution, argocd integration for NTS PROD - NTS UAT deployment and testing support | G129: Trieu Bao Lam | H129: DevOps | I129: FPT | J129: 8
A130: Sep-26 | B130: 46282 | C130: Project Task | D130: CRM | E130: - Prepare helmchart, persistent volume solution, argocd integration for NTS PROD - NTS UAT deployment and testing support | G130: Trieu Bao Lam | H130: DevOps | I130: FPT | J130: 8
A131: Sep-26 | B131: 46283 | C131: Project Task | D131: CRM | E131: - Prepare helmchart, persistent volume solution, argocd integration for NTS PROD - NTS UAT deployment and testing support | G131: Trieu Bao Lam | H131: DevOps | I131: FPT | J131: 8
... A139: Sep-26 | B139: 46295 | C139: Project Task | D139: CRM | E139: - Test EAI - NTS PROD/UAT deployment and testing support | G139: Trieu Bao Lam | H139: DevOps | I139: FPT | J139: 8
A140: Sep-26 | B140: 46266 | C140: Leave | D140: Leave | E140: Leave | F140: Annual Leave | G140: Ha Tuan Hoang | H140: EAI | I140: FPT | J140: 8
A141: Sep-26 | B141: 46267 | C141: Leave | D141: Leave | E141: Leave | F141: Annual Leave | G141: Ha Tuan Hoang | H141: EAI | I141: FPT | J141: 8
A142: Sep-26 | B142: 46268 | C142: Project Task | D142: EAI | E142: Prepare for EAI Proxy deployment support | F142: Deployment support | G142: Ha Tuan Hoang | H142: EAI | I142: FPT | J142: 8
A143: Sep-26 | B143: 46269 | C143: Project Task | D143: EAI | E143: Prepare for EAI Proxy deployment support | F143: Deployment support | G143: Ha Tuan Hoang | H143: EAI | I143: FPT | J143: 8
A144: Sep-26 | B144: 46272 | C144: Project Task | D144: PH | E144: EAI deployment supoort testing | G144: Ha Tuan Hoang | H144: EAI | I144: FPT | J144: 8
A145: Sep-26 | B145: 46273 | C145: Project Task | D145: EAI | E145: EAI deployment supoort testing | G145: Ha Tuan Hoang | H145: EAI | I145: FPT | J145: 8
A146: Sep-26 | B146: 46274 | C146: Project Task | D146: EAI | E146: EAI deployment supoort testing | G146: Ha Tuan Hoang | H146: EAI | I146: FPT | J146: 8
A147: Sep-26 | B147: 46275 | C147: Project Task | D147: EAI | E147: Unit testing Order process of IOM | G147: Ha Tuan Hoang | H147: EAI | I147: FPT | J147: 8
A148: Sep-26 | B148: 46276 | C148: Project Task | D148: EAI | E148: Unit testing Order process of IOM | G148: Ha Tuan Hoang | H148: EAI | I148: FPT | J148: 8
A149: Sep-26 | B149: 46279 | C149: Project Task | D149: EAI | E149: Review and testing IOM, SPL modules | G149: Ha Tuan Hoang | H149: EAI | I149: FPT | J149: 8
A150: Sep-26 | B150: 46280 | C150: Project Task | D150: EAI | E150: Review and testing IOM, SPL modules | G150: Ha Tuan Hoang | H150: EAI | I150: FPT | J150: 8
A151: Sep-26 | B151: 46281 | C151: Project Task | D151: EAI | E151: Review and testing IOM, SPL modules | G151: Ha Tuan Hoang | H151: EAI | I151: FPT | J151: 8
A152: Sep-26 | B152: 46282 | C152: Project Task | D152: EAI | E152: Review and testing IOM, SPL modules | G152: Ha Tuan Hoang | H152: EAI | I152: FPT | J152: 8
A153: Sep-26 | B153: 46283 | C153: Project Task | D153: EAI | E153: Review and testing IOM, SPL modules | G153: Ha Tuan Hoang | H153: EAI | I153: FPT | J153: 8
A154: Sep-26 | B154: 46286 | C154: Project Task | D154: EAI | E154: SPL poller processor unit testing | G154: Ha Tuan Hoang | H154: EAI | I154: FPT | J154: 8
A155: Sep-26 | B155: 46287 | C155: Project Task | D155: EAI | E155: SPL poller processor unit testing | G155: Ha Tuan Hoang | H155: EAI | I155: FPT | J155: 8
... A161: Sep-26 | B161: 46295 | C161: Project Task | D161: EAI | E161: Testing and fixing iom_order_tracking_gui issues | G161: Ha Tuan Hoang | H161: EAI | I161: FPT | J161: 8
A162: Sep-26 | B162: 46266 | C162: Leave | D162: Leave | E162: Leave | F162: Annual Leave | G162: Phan Van Manh | H162: EAI | I162: FPT | J162: 8
A163: Sep-26 | B163: 46267 | C163: Leave | D163: Leave | E163: Leave | F163: Annual Leave | G163: Phan Van Manh | H163: EAI | I163: FPT | J163: 8
A164: Sep-26 | B164: 46268 | C164: Project Task | D164: EAI | E164: Review and fixing issue for EAI IOM modules | G164: Phan Van Manh | H164: EAI | I164: FPT | J164: 8
A165: Sep-26 | B165: 46269 | C165: Project Task | D165: PH | E165: Review and fixing issue for EAI IOM modules | G165: Phan Van Manh | H165: EAI | I165: FPT | J165: 8
A166: Sep-26 | B166: 46272 | C166: Project Task | D166: EAI | E166: EAI deployment supoort testing | G166: Phan Van Manh | H166: EAI | I166: FPT | J166: 8
...

Sheet Summary
A1: Month | B1: 46266
A2: No | B2: Name | C2: Fsoft Account | D2: Team | E2: Location | F2: Total MM | G2: Calendar WD per Month | H2: Actual Normal Working days | I2: OT Weekdays | J2: OT Weekends | K2: OT Holidays | L2: Leave occur | M2: Payable Leave days | N2: Leave Balance- Up to each month | O2: Leave Balance- After each month | P2: Used Annual Leaves | Q2: Days off in lieu per month | R2: Used Days off in lieu
A3: =ROW()-2 -> 1 | B3: Dao Manh Ha | C3: HaDM | D3: EAI | E3: Long onsite | F3: =IFERROR(IF(Summary[[#This Row],[Actual Normal Working days]]=0,0,(Summary[[#This Row],[Actual Normal Working days]]+Summary[[#This Row],[Payable Leave days]])/Summary[[#This Row],[Calendar WD per Month]]),0) -> 1 | G3: =INDEX(Time!$D$3:$O$3,MATCH(Summary!$B$1,Time!$D$1:$O$1,0)) -> 22 | H3: =SUMIFS(Timesheet!J:J,Timesheet!G:G,Summary!B3,Timesheet!C:C,"Project Task")/8 -> 22 | I3: =SUMIFS(Timesheet!J:J,Timesheet!G:G,Summary!B3,Timesheet!C:C,"Weekday support")/8 -> 0 | J3: =SUMIFS(Timesheet!J:J,Timesheet!G:G,Summary!B3,Timesheet!C:C,"Weekend support")/8 -> 3 | K3: =SUMIFS(Timesheet!J:J,Timesheet!G:G,Summary!B3,Timesheet!C:C,"PH Support")/8 -> 0 | L3: =(SUMIFS(Timesheet!J:J,Timesheet!G:G,Summary[[#This Row],[Name]],Timesheet!C:C,"Leave")+SUMIFS(Timesheet!J:J,Timesheet!G:G,Summary[[#This Row],[Name]],Timesheet!C:C,"Half-day Leave")+SUMIFS(Timesheet!J:J,Timesheet!G:G,Summary[[#This Row],[Name]],Timesheet!C:C,"Comp-Off / Off-in-Lieu"))/8 -> 0 | M3: =IF(Summary[[#This Row],[Days off in lieu per month]]>0,IF(Summary[[#This Row],[Leave occur]]<=(Summary[[#This Row],[Leave Balance- Up to each month]]+Summary[[#This Row],[Days off in lieu per month]]),Summary[[#This Row],[Leave occur]],Summary[[#This Row],[Leave Balance- Up to each month]]+Summary[[#This Row],[Days off in lieu per month]]),IF(Summary[[#This Row],[Leave occur]]<=Summary[[#This Row],[Leave Balance- Up to each month]],Summary[[#This Row],[Leave occur]],Summary[[#This Row],[Leave Balance- Up to each month]])) -> 0 | N3: 11 | O3: =Summary[[#This Row],[Leave Balance- Up to each month]]-Summary[[#This Row],[Used Annual Leaves]] -> 11 | P3: =Summary[[#This Row],[Payable Leave days]]-Summary[[#This Row],[Used Days off in lieu]] -> 0 | Q3: =SUM(Summary[[#This Row],[OT Weekdays]:[OT Holidays]]) -> 3 | R3: =IF(AND(Summary[[#This Row],[Days off in lieu per month]]>0,Summary[[#This Row],[Payable Leave days]]>0),IF(AND(Summary[[#This Row],[Leave occur]]>0,Summary[[#This Row],[Leave occur]]<=Summary[[#This Row],[Days off in lieu per month]]),Summary[[#This Row],[Leave occur]],Summary[[#This Row],[Days off in lieu per month]]),0) -> 0
A4: =ROW()-2 -> 2 | B4: Duong Xuan Tung | C4: TungDX9 | D4: EAI | E4: Offshore | F4: =IFERROR(IF(Summary[[#This Row],[Actual Normal Working days]]=0,0,(Summary[[#This Row],[Actual Normal Working days]]+Summary[[#This Row],[Payable Leave days]])/Summary[[#This Row],[Calendar WD per Month]]),0) -> 1 | G4: =INDEX(Time!$D$3:$O$3,MATCH(Summary!$B$1,Time!$D$1:$O$1,0)) -> 22 | H4: =SUMIFS(Timesheet!J:J,Timesheet!G:G,Summary!B4,Timesheet!C:C,"Project Task")/8 -> 20 | I4: =SUMIFS(Timesheet!J:J,Timesheet!G:G,Summary!B4,Timesheet!C:C,"Weekday support")/8 -> 0 | J4: =SUMIFS(Timesheet!J:J,Timesheet!G:G,Summary!B4,Timesheet!C:C,"Weekend support")/8 -> 0 | K4: =SUMIFS(Timesheet!J:J,Timesheet!G:G,Summary!B4,Timesheet!C:C,"PH Support")/8 -> 0 | L4: =(SUMIFS(Timesheet!J:J,Timesheet!G:G,Summary[[#This Row],[Name]],Timesheet!C:C,"Leave")+SUMIFS(Timesheet!J:J,Timesheet!G:G,Summary[[#This Row],[Name]],Timesheet!C:C,"Half-day Leave")+SUMIFS(Timesheet!J:J,Timesheet!G:G,Summary[[#This Row],[Name]],Timesheet!C:C,"Comp-Off / Off-in-Lieu"))/8 -> 2 | M4: =IF(Summary[[#This Row],[Days off in lieu per month]]>0,IF(Summary[[#This Row],[Leave occur]]<=(Summary[[#This Row],[Leave Balance- Up to each month]]+Summary[[#This Row],[Days off in lieu per month]]),Summary[[#This Row],[Leave occur]],Summary[[#This Row],[Leave Balance- Up to each month]]+Summary[[#This Row],[Days off in lieu per month]]),IF(Summary[[#This Row],[Leave occur]]<=Summary[[#This Row],[Leave Balance- Up to each month]],Summary[[#This Row],[Leave occur]],Summary[[#This Row],[Leave Balance- Up to each month]])) -> 2 | N4: 9.5 | O4: =Summary[[#This Row],[Leave Balance- Up to each month]]-Summary[[#This Row],[Used Annual Leaves]] -> 7.5 | P4: =Summary[[#This Row],[Payable Leave days]]-Summary[[#This Row],[Used Days off in lieu]] -> 2 | Q4: =SUM(Summary[[#This Row],[OT Weekdays]:[OT Holidays]]) -> 0 | R4: =IF(AND(Summary[[#This Row],[Days off in lieu per month]]>0,Summary[[#This Row],[Payable Leave days]]>0),IF(AND(Summary[[#This Row],[Leave occur]]>0,Summary[[#This Row],[Leave occur]]<=Summary[[#This Row],[Days off in lieu per month]]),Summary[[#This Row],[Leave occur]],Summary[[#This Row],[Days off in lieu per month]]),0) -> 0
A5: =ROW()-2 -> 3 | B5: Mary Anne Fabia | C5: Maryanne.fabia | D5: AMS | E5: Offshore | F5: =IFERROR(IF(Summary[[#This Row],[Actual Normal Working days]]=0,0,(Summary[[#This Row],[Actual Normal Working days]]+Summary[[#This Row],[Payable Leave days]])/Summary[[#This Row],[Calendar WD per Month]]),0) -> 1 | G5: =INDEX(Time!$D$3:$O$3,MATCH(Summary!$B$1,Time!$D$1:$O$1,0)) -> 22 | H5: =SUMIFS(Timesheet!J:J,Timesheet!G:G,Summary!B5,Timesheet!C:C,"Project Task")/8 -> 21 | I5: =SUMIFS(Timesheet!J:J,Timesheet!G:G,Summary!B5,Timesheet!C:C,"Weekday support")/8 -> 0 | J5: =SUMIFS(Timesheet!J:J,Timesheet!G:G,Summary!B5,Timesheet!C:C,"Weekend support")/8 -> 1 | K5: =SUMIFS(Timesheet!J:J,Timesheet!G:G,Summary!B5,Timesheet!C:C,"PH Support")/8 -> 0 | L5: =(SUMIFS(Timesheet!J:J,Timesheet!G:G,Summary[[#This Row],[Name]],Timesheet!C:C,"Leave")+SUMIFS(Timesheet!J:J,Timesheet!G:G,Summary[[#This Row],[Name]],Timesheet!C:C,"Half-day Leave")+SUMIFS(Timesheet!J:J,Timesheet!G:G,Summary[[#This Row],[Name]],Timesheet!C:C,"Comp-Off / Off-in-Lieu"))/8 -> 1 | M5: =IF(Summary[[#This Row],[Days off in lieu per month]]>0,IF(Summary[[#This Row],[Leave occur]]<=(Summary[[#This Row],[Leave Balance- Up to each month]]+Summary[[#This Row],[Days off in lieu per month]]),Summary[[#This Row],[Leave occur]],Summary[[#This Row],[Leave Balance- Up to each month]]+Summary[[#This Row],[Days off in lieu per month]]),IF(Summary[[#This Row],[Leave occur]]<=Summary[[#This Row],[Leave Balance- Up to each month]],Summary[[#This Row],[Leave occur]],Summary[[#This Row],[Leave Balance- Up to each month]])) -> 1 | N5: 10 | O5: =Summary[[#This Row],[Leave Balance- Up to each month]]-Summary[[#This Row],[Used Annual Leaves]] -> 10 | P5: =Summary[[#This Row],[Payable Leave days]]-Summary[[#This Row],[Used Days off in lieu]] -> 0 | Q5: =SUM(Summary[[#This Row],[OT Weekdays]:[OT Holidays]]) -> 1 | R5: =IF(AND(Summary[[#This Row],[Days off in lieu per month]]>0,Summary[[#This Row],[Payable Leave days]]>0),IF(AND(Summary[[#This Row],[Leave occur]]>0,Summary[[#This Row],[Leave occur]]<=Summary[[#This Row],[Days off in lieu per month]]),Summary[[#This Row],[Leave occur]],Summary[[#This Row],[Days off in lieu per month]]),0) -> 1
A6: =ROW()-2 -> 4 | B6: Santos Conrado Jr | C6: Santoscj | D6: AMS | E6: Offshore | F6: =IFERROR(IF(Summary[[#This Row],[Actual Normal Working days]]=0,0,(Summary[[#This Row],[Actual Normal Working days]]+Summary[[#This Row],[Payable Leave days]])/Summary[[#This Row],[Calendar WD per Month]]),0) -> 1 | G6: =INDEX(Time!$D$3:$O$3,MATCH(Summary!$B$1,Time!$D$1:$O$1,0)) -> 22 | H6: =SUMIFS(Timesheet!J:J,Timesheet!G:G,Summary!B6,Timesheet!C:C,"Project Task")/8 -> 18 | I6: =SUMIFS(Timesheet!J:J,Timesheet!G:G,Summary!B6,Timesheet!C:C,"Weekday support")/8 -> 0 | J6: =SUMIFS(Timesheet!J:J,Timesheet!G:G,Summary!B6,Timesheet!C:C,"Weekend support")/8 -> 1 | K6: =SUMIFS(Timesheet!J:J,Timesheet!G:G,Summary!B6,Timesheet!C:C,"PH Support")/8 -> 0 | L6: =(SUMIFS(Timesheet!J:J,Timesheet!G:G,Summary[[#This Row],[Name]],Timesheet!C:C,"Leave")+SUMIFS(Timesheet!J:J,Timesheet!G:G,Summary[[#This Row],[Name]],Timesheet!C:C,"Half-day Leave")+SUMIFS(Timesheet!J:J,Timesheet!G:G,Summary[[#This Row],[Name]],Timesheet!C:C,"Comp-Off / Off-in-Lieu"))/8 -> 4 | M6: =IF(Summary[[#This Row],[Days off in lieu per month]]>0,IF(Summary[[#This Row],[Leave occur]]<=(Summary[[#This Row],[Leave Balance- Up to each month]]+Summary[[#This Row],[Days off in lieu per month]]),Summary[[#This Row],[Leave occur]],Summary[[#This Row],[Leave Balance- Up to each month]]+Summary[[#This Row],[Days off in lieu per month]]),IF(Summary[[#This Row],[Leave occur]]<=Summary[[#This Row],[Leave Balance- Up to each month]],Summary[[#This Row],[Leave occur]],Summary[[#This Row],[Leave Balance- Up to each month]])) -> 4 | N6: 10 | O6: =Summary[[#This Row],[Leave Balance- Up to each month]]-Summary[[#This Row],[Used Annual Leaves]] -> 7 | P6: =Summary[[#This Row],[Payable Leave days]]-Summary[[#This Row],[Used Days off in lieu]] -> 3 | Q6: =SUM(Summary[[#This Row],[OT Weekdays]:[OT Holidays]]) -> 1 | R6: =IF(AND(Summary[[#This Row],[Days off in lieu per month]]>0,Summary[[#This Row],[Payable Leave days]]>0),IF(AND(Summary[[#This Row],[Leave occur]]>0,Summary[[#This Row],[Leave occur]]<=Summary[[#This Row],[Days off in lieu per month]]),Summary[[#This Row],[Leave occur]],Summary[[#This Row],[Days off in lieu per month]]),0) -> 1
A7: =ROW()-2 -> 5 | B7: Nguyen Hoang | C7: HoangN22 | D7: DevOps | E7: Offshore | F7: =IFERROR(IF(Summary[[#This Row],[Actual Normal Working days]]=0,0,(Summary[[#This Row],[Actual Normal Working days]]+Summary[[#This Row],[Payable Leave days]])/Summary[[#This Row],[Calendar WD per Month]]),0) -> 1 | G7: =INDEX(Time!$D$3:$O$3,MATCH(Summary!$B$1,Time!$D$1:$O$1,0)) -> 22 | H7: =SUMIFS(Timesheet!J:J,Timesheet!G:G,Summary!B7,Timesheet!C:C,"Project Task")/8 -> 19 | I7: =SUMIFS(Timesheet!J:J,Timesheet!G:G,Summary!B7,Timesheet!C:C,"Weekday support")/8 -> 0 | J7: =SUMIFS(Timesheet!J:J,Timesheet!G:G,Summary!B7,Timesheet!C:C,"Weekend support")/8 -> 1 | K7: =SUMIFS(Timesheet!J:J,Timesheet!G:G,Summary!B7,Timesheet!C:C,"PH Support")/8 -> 0 | L7: =(SUMIFS(Timesheet!J:J,Timesheet!G:G,Summary[[#This Row],[Name]],Timesheet!C:C,"Leave")+SUMIFS(Timesheet!J:J,Timesheet!G:G,Summary[[#This Row],[Name]],Timesheet!C:C,"Half-day Leave")+SUMIFS(Timesheet!J:J,Timesheet!G:G,Summary[[#This Row],[Name]],Timesheet!C:C,"Comp-Off / Off-in-Lieu"))/8 -> 3 | M7: =IF(Summary[[#This Row],[Days off in lieu per month]]>0,IF(Summary[[#This Row],[Leave occur]]<=(Summary[[#This Row],[Leave Balance- Up to each month]]+Summary[[#This Row],[Days off in lieu per month]]),Summary[[#This Row],[Leave occur]],Summary[[#This Row],[Leave Balance- Up to each month]]+Summary[[#This Row],[Days off in lieu per month]]),IF(Summary[[#This Row],[Leave occur]]<=Summary[[#This Row],[Leave Balance- Up to each month]],Summary[[#This Row],[Leave occur]],Summary[[#This Row],[Leave Balance- Up to each month]])) -> 3 | N7: 9 | O7: =Summary[[#This Row],[Leave Balance- Up to each month]]-Summary[[#This Row],[Used Annual Leaves]] -> 7 | P7: =Summary[[#This Row],[Payable Leave days]]-Summary[[#This Row],[Used Days off in lieu]] -> 2 | Q7: =SUM(Summary[[#This Row],[OT Weekdays]:[OT Holidays]]) -> 1 | R7: =IF(AND(Summary[[#This Row],[Days off in lieu per month]]>0,Summary[[#This Row],[Payable Leave days]]>0),IF(AND(Summary[[#This Row],[Leave occur]]>0,Summary[[#This Row],[Leave occur]]<=Summary[[#This Row],[Days off in lieu per month]]),Summary[[#This Row],[Leave occur]],Summary[[#This Row],[Days off in lieu per month]]),0) -> 1
A8: =ROW()-2 -> 6 | B8: Trieu Bao Lam | C8: Lamtb2 | D8: EAI | E8: Offshore | F8: =IFERROR(IF(Summary[[#This Row],[Actual Normal Working days]]=0,0,(Summary[[#This Row],[Actual Normal Working days]]+Summary[[#This Row],[Payable Leave days]])/Summary[[#This Row],[Calendar WD per Month]]),0) -> 1 | G8: =INDEX(Time!$D$3:$O$3,MATCH(Summary!$B$1,Time!$D$1:$O$1,0)) -> 22 | H8: =SUMIFS(Timesheet!J:J,Timesheet!G:G,Summary!B8,Timesheet!C:C,"Project Task")/8 -> 20 | I8: =SUMIFS(Timesheet!J:J,Timesheet!G:G,Summary!B8,Timesheet!C:C,"Weekday support")/8 -> 0 | J8: =SUMIFS(Timesheet!J:J,Timesheet!G:G,Summary!B8,Timesheet!C:C,"Weekend support")/8 -> 0 | K8: =SUMIFS(Timesheet!J:J,Timesheet!G:G,Summary!B8,Timesheet!C:C,"PH Support")/8 -> 0 | L8: =(SUMIFS(Timesheet!J:J,Timesheet!G:G,Summary[[#This Row],[Name]],Timesheet!C:C,"Leave")+SUMIFS(Timesheet!J:J,Timesheet!G:G,Summary[[#This Row],[Name]],Timesheet!C:C,"Half-day Leave")+SUMIFS(Timesheet!J:J,Timesheet!G:G,Summary[[#This Row],[Name]],Timesheet!C:C,"Comp-Off / Off-in-Lieu"))/8 -> 2 | M8: =IF(Summary[[#This Row],[Days off in lieu per month]]>0,IF(Summary[[#This Row],[Leave occur]]<=(Summary[[#This Row],[Leave Balance- Up to each month]]+Summary[[#This Row],[Days off in lieu per month]]),Summary[[#This Row],[Leave occur]],Summary[[#This Row],[Leave Balance- Up to each month]]+Summary[[#This Row],[Days off in lieu per month]]),IF(Summary[[#This Row],[Leave occur]]<=Summary[[#This Row],[Leave Balance- Up to each month]],Summary[[#This Row],[Leave occur]],Summary[[#This Row],[Leave Balance- Up to each month]])) -> 2 | N8: 7 | O8: =Summary[[#This Row],[Leave Balance- Up to each month]]-Summary[[#This Row],[Used Annual Leaves]] -> 5 | P8: =Summary[[#This Row],[Payable Leave days]]-Summary[[#This Row],[Used Days off in lieu]] -> 2 | Q8: =SUM(Summary[[#This Row],[OT Weekdays]:[OT Holidays]]) -> 0 | R8: =IF(AND(Summary[[#This Row],[Days off in lieu per month]]>0,Summary[[#This Row],[Payable Leave days]]>0),IF(AND(Summary[[#This Row],[Leave occur]]>0,Summary[[#This Row],[Leave occur]]<=Summary[[#This Row],[Days off in lieu per month]]),Summary[[#This Row],[Leave occur]],Summary[[#This Row],[Days off in lieu per month]]),0) -> 0
A9: =ROW()-2 -> 7 | B9: Ha Tuan Hoang | C9: HoangHT12 | D9: EAI | E9: Offshore | F9: =IFERROR(IF(Summary[[#This Row],[Actual Normal Working days]]=0,0,(Summary[[#This Row],[Actual Normal Working days]]+Summary[[#This Row],[Payable Leave days]])/Summary[[#This Row],[Calendar WD per Month]]),0) -> 1 | G9: =INDEX(Time!$D$3:$O$3,MATCH(Summary!$B$1,Time!$D$1:$O$1,0)) -> 22 | H9: =SUMIFS(Timesheet!J:J,Timesheet!G:G,Summary!B9,Timesheet!C:C,"Project Task")/8 -> 20 | I9: =SUMIFS(Timesheet!J:J,Timesheet!G:G,Summary!B9,Timesheet!C:C,"Weekday support")/8 -> 0 | J9: =SUMIFS(Timesheet!J:J,Timesheet!G:G,Summary!B9,Timesheet!C:C,"Weekend support")/8 -> 0 | K9: =SUMIFS(Timesheet!J:J,Timesheet!G:G,Summary!B9,Timesheet!C:C,"PH Support")/8 -> 0 | L9: =(SUMIFS(Timesheet!J:J,Timesheet!G:G,Summary[[#This Row],[Name]],Timesheet!C:C,"Leave")+SUMIFS(Timesheet!J:J,Timesheet!G:G,Summary[[#This Row],[Name]],Timesheet!C:C,"Half-day Leave")+SUMIFS(Timesheet!J:J,Timesheet!G:G,Summary[[#This Row],[Name]],Timesheet!C:C,"Comp-Off / Off-in-Lieu"))/8 -> 2 | M9: =IF(Summary[[#This Row],[Days off in lieu per month]]>0,IF(Summary[[#This Row],[Leave occur]]<=(Summary[[#This Row],[Leave Balance- Up to each month]]+Summary[[#This Row],[Days off in lieu per month]]),Summary[[#This Row],[Leave occur]],Summary[[#This Row],[Leave Balance- Up to each month]]+Summary[[#This Row],[Days off in lieu per month]]),IF(Summary[[#This Row],[Leave occur]]<=Summary[[#This Row],[Leave Balance- Up to each month]],Summary[[#This Row],[Leave occur]],Summary[[#This Row],[Leave Balance- Up to each month]])) -> 2 | N9: 8 | O9: =Summary[[#This Row],[Leave Balance- Up to each month]]-Summary[[#This Row],[Used Annual Leaves]] -> 6 | P9: =Summary[[#This Row],[Payable Leave days]]-Summary[[#This Row],[Used Days off in lieu]] -> 2 | Q9: =SUM(Summary[[#This Row],[OT Weekdays]:[OT Holidays]]) -> 0 | R9: =IF(AND(Summary[[#This Row],[Days off in lieu per month]]>0,Summary[[#This Row],[Payable Leave days]]>0),IF(AND(Summary[[#This Row],[Leave occur]]>0,Summary[[#This Row],[Leave occur]]<=Summary[[#This Row],[Days off in lieu per month]]),Summary[[#This Row],[Leave occur]],Summary[[#This Row],[Days off in lieu per month]]),0) -> 0
A10: =ROW()-2 -> 8 | B10: Phan Van Manh | C10: ManhPV16 | D10: EAI | E10: Offshore | F10: =IFERROR(IF(Summary[[#This Row],[Actual Normal Working days]]=0,0,(Summary[[#This Row],[Actual Normal Working days]]+Summary[[#This Row],[Payable Leave days]])/Summary[[#This Row],[Calendar WD per Month]]),0) -> 1 | G10: =INDEX(Time!$D$3:$O$3,MATCH(Summary!$B$1,Time!$D$1:$O$1,0)) -> 22 | H10: =SUMIFS(Timesheet!J:J,Timesheet!G:G,Summary!B10,Timesheet!C:C,"Project Task")/8 -> 19 | I10: =SUMIFS(Timesheet!J:J,Timesheet!G:G,Summary!B10,Timesheet!C:C,"Weekday support")/8 -> 0 | J10: =SUMIFS(Timesheet!J:J,Timesheet!G:G,Summary!B10,Timesheet!C:C,"Weekend support")/8 -> 0 | K10: =SUMIFS(Timesheet!J:J,Timesheet!G:G,Summary!B10,Timesheet!C:C,"PH Support")/8 -> 0 | L10: =(SUMIFS(Timesheet!J:J,Timesheet!G:G,Summary[[#This Row],[Name]],Timesheet!C:C,"Leave")+SUMIFS(Timesheet!J:J,Timesheet!G:G,Summary[[#This Row],[Name]],Timesheet!C:C,"Half-day Leave")+SUMIFS(Timesheet!J:J,Timesheet!G:G,Summary[[#This Row],[Name]],Timesheet!C:C,"Comp-Off / Off-in-Lieu"))/8 -> 3 | M10: =IF(Summary[[#This Row],[Days off in lieu per month]]>0,IF(Summary[[#This Row],[Leave occur]]<=(Summary[[#This Row],[Leave Balance- Up to each month]]+Summary[[#This Row],[Days off in lieu per month]]),Summary[[#This Row],[Leave occur]],Summary[[#This Row],[Leave Balance- Up to each month]]+Summary[[#This Row],[Days off in lieu per month]]),IF(Summary[[#This Row],[Leave occur]]<=Summary[[#This Row],[Leave Balance- Up to each month]],Summary[[#This Row],[Leave occur]],Summary[[#This Row],[Leave Balance- Up to each month]])) -> 3 | N10: 8 | O10: =Summary[[#This Row],[Leave Balance- Up to each month]]-Summary[[#This Row],[Used Annual Leaves]] -> 5 | P10: =Summary[[#This Row],[Payable Leave days]]-Summary[[#This Row],[Used Days off in lieu]] -> 3 | Q10: =SUM(Summary[[#This Row],[OT Weekdays]:[OT Holidays]]) -> 0 | R10: =IF(AND(Summary[[#This Row],[Days off in lieu per month]]>0,Summary[[#This Row],[Payable Leave days]]>0),IF(AND(Summary[[#This Row],[Leave occur]]>0,Summary[[#This Row],[Leave occur]]<=Summary[[#This Row],[Days off in lieu per month]]),Summary[[#This Row],[Leave occur]],Summary[[#This Row],[Days off in lieu per month]]),0) -> 0

Sheet Time
D1: 46023 | E1: 46054 | F1: 46082 | G1: 46113 | H1: 46143 | I1: 46174 | J1: 46204 | K1: 46235 | L1: 46266 | M1: 46296 | N1: 46327 | O1: 46357
D2: 46053 | E2: 46081 | F2: 46112 | G2: 46142 | H2: 46173 | I2: 46203 | J2: 46234 | K2: 46265 | L2: 46295 | M2: 46326 | N2: 46356 | O2: 46387
A3: Singapore Holidays | D3: =NETWORKDAYS(D1,D2,D4:D6) -> 21 | E3: =NETWORKDAYS(E1,E2,E4:E6) -> 18 | F3: =NETWORKDAYS(F1,F2,F4:F6) -> 22 | G3: =NETWORKDAYS(G1,G2,G4:G6) -> 21 | H3: =NETWORKDAYS(H1,H2,H4:H6) -> 19 | I3: =NETWORKDAYS(I1,I2,I4:I6) -> 21 | J3: =NETWORKDAYS(J1,J2,J4:J6) -> 23 | K3: =NETWORKDAYS(K1,K2,K4:K6) -> 20 | ... O3: =NETWORKDAYS(O1,O2,O4:O6) -> 22
D4: 46023 | E4: 46070 | G4: 46115 | H4: 46143 | I4: 46174 | K4: 46244 | N4: 46335 | O4: 46381
E5: 46071 | H5: 46169
